lc_api_manager/__init__.py
lc_api_manager/api_client.py
lc_api_manager/api_manager.py
lc_api_manager-0.1.1.dist-info/LICENSE
lc_api_manager-0.1.1.dist-info/METADATA
lc_api_manager-0.1.1.dist-info/WHEEL
lc_api_manager-0.1.1.dist-info/top_level.txt
lc_api_manager-0.1.1.dist-info/RECORD
