Metadata-Version: 2.1
Name: lc-api-manager
Version: 0.1.1
Summary: UNKNOWN
Home-page: https://github.com/libcommon/api-manager-py
Author: libcommon
Author-email: libcommon@protonmail.com
License: UNKNOWN
Project-URL: Issue Tracker, https://github.com/libcommon/api-manager-py/issues
Project-URL: Releases, https://github.com/libcommon/api-manager-py/releases
Platform: UNKNOWN
Classifier: Intended Audience :: Developers
Classifier: Programming Language :: Python :: 3
Classifier: License :: OSI Approved :: MIT License
Classifier: Operating System :: OS Independent
Requires-Python: >=3.6
Requires-Dist: lc-cache
